{"paths":{},"types":[],"uuids":["1d2uunKUxKy49FpUjKxC/f","29FYIk+N1GYaeWH/q1NxQO","4d+5bbohpJaJvkr/WUr7rq","a2MjXRFdtLlYQ5ouAFv/+R","c6KC7ivzxH8ax2/MMuudLf","e97GVMl6JHh5Ml5qEDdSGa","f0BIwQ8D5Ml7nTNQbh1YlS","062K5JfJ1IwqJbq0BQHaV3","0cqynuGwNHBYKEsrKRIRaE","118Pxu9AZL659tuf/OtLbv","16ImjaAeVA6K63y0xg4Tii","16JeGi3hhE/LsDL0vuwcqm","17/psUpztBDoK284zdEABX","25Rk96b3FK5JwSM1edQjLr","26alJ1Cr5E/oiSZJAv6mnq","2e+XJClQFGN6tN0uI18fEU","2frQu2j9JAhb3+Oruy9KBs","2f52GhHYVBSJ23ET2Koudv","31aJixJs9Gmopdbcz/MriM","32y2a4xeZDybbURUjOetiE","44LxHsVsxCF5NZaoL4X9TG","45SnPV/wBMFLdwilIcPUPL","47VQafedhHRL1IzWFl4mZl","54qctmOyhBsaneJzIXTSVW","56F5jpxMxMlpUWlKuwStiC","57DmzXVcdB2opTz3szjO8k","64+qA7tglOvLLn5xXl5zjN","69tZzpUdhFlZx2L+bFITlM","6ckW52yqRPDIW15VZZ427I","71VhFCTINJM6/Ky3oX9nBT","74BkCQFvpMd682J3GYk6IO","7cYn/1BIZMnaNNG7S/HNpY","7ci6peVWpAsIVtoAJjV//0","85gMLbtTtEibKHuahg5YrA","89xfu4IT5Etauo0nx2FL1B","899xw+chhNn5/nOWn9krNA","90K48sq5dB77+pNJR12J08","91BF2vBahKIYueKQOrjkhS","92rwtttpdJ1azDy1Wptd1p","9f3j57giBNZ7GwZm+cWw0c","a07+fT4ntN8pNdo3zm5Mqb","a1Vw3TmFVNx5STv3zbrIzg","a1vyWY31JNB4wIUi0OnB7d","a3MtNi8zZL5LBEm+Fa2gTw","a5mouA051H16Otsb7vg7Ti","a7W34BVgpA3LUTgb1/PgWh","abTCp2LU1KhrQNzcg1oYMC","acirIGcVdP/KCWOCqZZ0W7","b1AFHnHzxJ4a0dQae1EsVG","b1Fw+MR2xF+72xcnSWCO6V","b4P/PCArtIdIH38t6mlw8Y","b9aD1ga7pE1YcWcEQHlEL7","bbUA373mdOdaW99CPcL9Ib","bf+/N4dqNILY9rVZBS9HBW","c1FMiYNPpH044BBpmxpw0r","c1Pc3XULJHeKPEuvs+u0Gp","c6xqH9LHVPN6Bd8yQk5yNx","c7GWzUlUlAA4SwvJ05roAZ","c9J8xF42dOdLl2qTGcJdhI","ceCCJuSPhFrZA5UgLBMWYA","d9JkVLf4ZOZrjXlz3avcBJ","dbMe0Uj6JBBae7xvwdMo1/","df2o27K/RLU4wfsVLDwAbR","e3qwjxKRJHv5WtjQnSSz4M","e8G1QXQWJAD7ISKCBnIVwK","e8Ueib+qJEhL6mXAHdnwbi","eaI6BWS9pEBo7khmPa4QEP","f59w4xTiBEurIbefagoTyz","02bnWMvuVEs5tnoGDukJVz","02delMVqdBD70a/HSD99FK","0a9sfGUbxICbxfLq8uQAST","0b5FnJHTxBe5m6Aj7+HE+X","0drBlyWG5OAJ4oyDh3OuPq","0dzcwt3XtIVpGypyBtgiFl","14c/TR7WZNUK3slOgD3NDa","18ACjX9tNOKKrW41uULV7C","24vT0t279AsKXw5ot862o1","29/XcrlvROh5LrUZoK8Oy5","2cyUR8ZoJJXq5Hf3weBnQf","2c3g0FtEZH87a2YeDX+pEf","40kfIgG9ZL8by13PXDeFlu","46S7qYMsNJKYjts4DPbsk2","4fL1T5kwxEjrf9rSvQHvzi","50VTP9WKZM4L9zQQX4CXcs","537RXko5RCH5Xzse95/tN0","56aqyfUTRNoZeDZe5b2aZd","59GzFI7kVJvYsj4I6GJWx5","5act8IJlBOzKhoLYr3CQMx","5crNwlwxtJb7jOFM/r9mxZ","63qJ8YcglKb4Pt6zQX7p4w","6984LX2h5PkqMANgwyJh0W","6aLYkjw95Fv5Um/uEexFhU","73FIluljdK47CLU1m+BU6g","79s5JKhfFOO4zc/PrVBiLK","7aG8s7T11DY5bnbAGuqDR1","7eNB52CRlHQ5mBGGdyRxzF","7eak+ZihFAwqvX2Y32WvX9","8eVso434BPXbkePT2WaIkf","9e3pQyJEVFtKZZMMFbKuNd","a3b8WjAwFIeaTf7oJK3HPs","a4akU5ggJG2pgAcdx8Hw32","a4k23Pt6NNerNAjl/Crany","a47fis4L9NeI+zwP5dsw1j","aehCxepSpOVYH+7dBSIz2p","b1g0UsZpRI2bKr4QqeXtuv","bdkIJOr1VJDJilQP1fSCgW","bf9XljBIpL5p4761Yi6BYW","c4emyPXchJ57XDGca6duWE","cfhTZ6cGxA26yXebuqB7v5","d5W5nyW/pPJZg5f/kWZt4+","da+QEMbtRK05yHJvQwqlF3","e8D24DL15EPoz65zsbUzeb","ecpdLyjvZBwrvm+cedCcQy","edvZ1n4qtL6IC4WvsGNhYm","f3vTApxQ5Pv6V0Ev8iPsar","f3vg8ygC1L7qHhVDnL2ih3","f4kfLZtEBJerVwcp9aNbWU","f6Xb7UQ2pE35WopfCsNJvD"],"scenes":{"db://assets/scenes/game.fire":15,"db://assets/scenes/landing.fire":32,"db://assets/scenes/selectLevel.fire":7},"redirect":[69,0,112,0],"deps":["internal"],"packs":{"018bf47bf":[68,7,71,73,0,76,1,78,21,2,86,3,100,101,44,103,104,105,4,108,109,110,5,66,6],"0773556be":[70,8,72,74,75,0,1,77,79,15,80,21,2,82,83,85,87,88,89,26,91,92,93,94,95,96,97,98,3,43,99,102,47,106,107,4,62,5,66,113,6,114,115,116,67],"0a1b3b138":[46,117],"0f11ce6fc":[9,10,11,12,13,14,16,17,19,20,22,23,24,25,27,29,30,31,33,34,35,36,37,38,39,40,41,42,45,48,49,50,51,52,53,54,55,56,57,58,59,60,61,63,64,65],"0f1b73769":[0,1,81,2,84,26,90,32,3,44,4,111,5,6]},"name":"main","importBase":"import","nativeBase":"native","debug":false,"isZip":false,"encrypted":false,"versions":{"import":["018bf47bf","be86d","0773556be","91f09","0a1b3b138","15f63","0f11ce6fc","6b277","0f1b73769","08034",18,"e05a3",28,"ee988"],"native":[8,"e1cc4",9,"14920",10,"2192e",11,"be3c8",12,"55acd",13,"00296",14,"2ec55",16,"05159",17,"362cb",18,"004ac",19,"1e8e2",20,"df62a",22,"af125",23,"d7756",24,"34679",25,"fd8fd",27,"53f54",28,"78525",29,"c06a9",30,"60708",31,"092d3",33,"8e36c",34,"87e8a",35,"6aad2",36,"b517e",37,"1a476",38,"fd967",39,"8d42e",40,"6d9eb",41,"1b464",42,"02b4a",43,"84b53",45,"aaae9",46,"c7b4a",47,"635cc",48,"bfd1b",49,"7bd6a",50,"83fcc",51,"42cc5",52,"e624f",53,"452c9",54,"7d90b",55,"efba8",56,"b22f7",57,"2588c",58,"98bbd",59,"55c7b",60,"6f336",61,"5bc0e",62,"0d3bd",63,"9cca9",64,"f490a",65,"90cf4",67,"68380"]}}